pfsense_redactor/__init__.py
pfsense_redactor/__main__.py
pfsense_redactor/redactor.py
pfsense_redactor/version_checker.py
pfsense_redactor-1.0.10.dist-info/licenses/LICENSE
pfsense_redactor-1.0.10.dist-info/METADATA
pfsense_redactor-1.0.10.dist-info/WHEEL
pfsense_redactor-1.0.10.dist-info/entry_points.txt
pfsense_redactor-1.0.10.dist-info/top_level.txt
pfsense_redactor-1.0.10.dist-info/RECORD
