Metadata-Version: 2.4
Name: pfsense-redactor
Version: 1.0.10
Summary: Redacts secrets and optionally anonymises identifiers in pfSense config.xml exports for safe sharing
Author: pfSense Redactor Contributors
License: MIT
Project-URL: Homepage, https://github.com/grounzero/pfsense-redactor
Project-URL: Repository, https://github.com/grounzero/pfsense-redactor
Project-URL: Bug Tracker, https://github.com/grounzero/pfsense-redactor/issues
Project-URL: Documentation, https://github.com/grounzero/pfsense-redactor#readme
Project-URL: Changelog, https://github.com/grounzero/pfsense-redactor/blob/main/CHANGELOG.md
Project-URL: Source Code, https://github.com/grounzero/pfsense-redactor
Keywords: pfsense,netgate,firewall,configuration,config,config.xml,security,privacy,redaction,anonymiser,anonymizer,sanitiser,sanitizer,xml,vpn,wireguard,openvpn,ipsec
Classifier: Development Status :: 5 - Production/Stable
Classifier: Environment :: Console
Classifier: Intended Audience :: Information Technology
Classifier: Intended Audience :: System Administrators
Classifier: License :: OSI Approved :: MIT License
Classifier: Natural Language :: English
Classifier: Operating System :: OS Independent
Classifier: Programming Language :: Python :: 3
Classifier: Programming Language :: Python :: 3.9
Classifier: Programming Language :: Python :: 3.10
Classifier: Programming Language :: Python :: 3.11
Classifier: Programming Language :: Python :: 3.12
Classifier: Programming Language :: Python :: 3.13
Classifier: Programming Language :: Python :: Implementation :: CPython
Classifier: Topic :: Security
Classifier: Topic :: System :: Networking
Classifier: Topic :: System :: Networking :: Firewalls
Classifier: Topic :: System :: Systems Administration
Classifier: Topic :: Utilities
Requires-Python: >=3.9
License-File: LICENSE
Provides-Extra: dev
Requires-Dist: pytest==8.4.2; extra == "dev"
Requires-Dist: pytest-cov==7.0.0; extra == "dev"
Requires-Dist: pytest-xdist==3.8.0; extra == "dev"
Dynamic: license-file
